[
  {
    "resourceId": 262792,
    "assetId": 262792,
    "preferredPosition": "CB",
    "possiblePositions": ["CB", "RB"],
    "rating": 63,
    "metalId": 1,
    "preferredFoot": "Right",
    "skillMoves": 2,
    "playStyles": [],
    "playStylesPlus": [],
    "eaRolesPlus": [11],
    "eaRolesPlusPlus": [],
    "clubId": 543,
    "leagueId": 2076,
    "countryId": 4,
    "weakFoot": 4,
    "attributes": [70, 40, 51, 59, 60, 76],
    "metaRating": 63.32198154998407,
    "playerRoleId": 11,
    "canEvolve": true,
    "hasDynamicImage": false,
    "playerUrl": "https://assets.easysbc.io/fc26/players/262792.png",
    "newPlayer": false,
    "versionId": 1,
    "eaPlayerId": null,
    "untradeable": false,
    "owned": false,
    "name": "Felix Strauss",
    "cardName": "Strauss",
    "price": 200,
    "rolesPlus": [11],
    "rolesPlusPlus": [11]
  },
  {
    "resourceId": 206086,
    "assetId": 206086,
    "preferredPosition": "LB",
    "possiblePositions": ["LB", "LM"],
    "rating": 71,
    "metalId": 2,
    "preferredFoot": "Left",
    "skillMoves": 3,
    "playStyles": [],
    "playStylesPlus": [],
    "eaRolesPlus": [9],
    "eaRolesPlusPlus": [],
    "clubId": 114640,
    "leagueId": 39,
    "countryId": 14,
    "weakFoot": 2,
    "attributes": [67, 53, 67, 66, 70, 67],
    "metaRating": 63.321708743595394,
    "playerRoleId": 7,
    "canEvolve": true,
    "hasDynamicImage": false,
    "playerUrl": "https://assets.easysbc.io/fc26/players/206086.png",
    "newPlayer": false,
    "versionId": 0,
    "eaPlayerId": null,
    "untradeable": false,
    "owned": false,
    "name": "Harry Toffolo",
    "cardName": "Toffolo",
    "price": 200,
    "rolesPlus": [9],
    "rolesPlusPlus": [9]
  },
  {
    "resourceId": 238157,
    "assetId": 238157,
    "preferredPosition": "RB",
    "possiblePositions": ["RB", "RM"],
    "rating": 73,
    "metalId": 2,
    "preferredFoot": "Right",
    "skillMoves": 3,
    "playStyles": [],
    "playStylesPlus": [],
    "eaRolesPlus": [5],
    "eaRolesPlusPlus": [],
    "clubId": 17,
    "leagueId": 14,
    "countryId": 13,
    "weakFoot": 3,
    "attributes": [68, 45, 69, 70, 70, 69],
    "metaRating": 63.32151202289813,
    "playerRoleId": 3,
    "canEvolve": true,
    "hasDynamicImage": false,
    "playerUrl": "https://assets.easysbc.io/fc26/players/238157.png",
    "newPlayer": false,
    "versionId": 0,
    "eaPlayerId": null,
    "untradeable": false,
    "owned": false,
    "name": "Mads Roerslev",
    "cardName": "Roerslev",
    "price": 200,
    "rolesPlus": [5],
    "rolesPlusPlus": [5]
  },
  {
    "resourceId": 242623,
    "assetId": 242623,
    "preferredPosition": "CB",
    "possiblePositions": ["CB"],
    "rating": 70,
    "metalId": 2,
    "preferredFoot": "Right",
    "skillMoves": 2,
    "playStyles": [19],
    "playStylesPlus": [],
    "eaRolesPlus": [13],
    "eaRolesPlusPlus": [],
    "clubId": 918,
    "leagueId": 41,
    "countryId": 36,
    "weakFoot": 3,
    "attributes": [62, 37, 60, 61, 69, 74],
    "metaRating": 63.32094307070385,
    "playerRoleId": 12,
    "canEvolve": true,
    "hasDynamicImage": false,
    "playerUrl": "https://assets.easysbc.io/fc26/players/242623.png",
    "newPlayer": false,
    "versionId": 0,
    "eaPlayerId": null,
    "untradeable": false,
    "owned": false,
    "name": "Odin Luraas Bj\u00f8rtuft",
    "cardName": "Bj\u00f8rtuft",
    "price": 200,
    "rolesPlus": [13],
    "rolesPlusPlus": [13]
  },
  {
    "resourceId": 213948,
    "assetId": 213948,
    "preferredPosition": "CAM",
    "possiblePositions": ["CAM", "CM", "RM"],
    "rating": 68,
    "metalId": 2,
    "preferredFoot": "Right",
    "skillMoves": 3,
    "playStyles": [20, 27],
    "playStylesPlus": [],
    "eaRolesPlus": [22, 26, 31, 33],
    "eaRolesPlusPlus": [],
    "clubId": 698,
    "leagueId": 39,
    "countryId": 95,
    "weakFoot": 3,
    "attributes": [73, 64, 64, 73, 61, 62],
    "metaRating": 63.31951882497406,
    "playerRoleId": 24,
    "canEvolve": true,
    "hasDynamicImage": false,
    "playerUrl": "https://assets.easysbc.io/fc26/players/213948.png",
    "newPlayer": false,
    "versionId": 0,
    "eaPlayerId": null,
    "untradeable": false,
    "owned": false,
    "name": "Duane Holmes",
    "cardName": "Holmes",
    "price": 200,
    "rolesPlus": [22, 26, 31, 33],
    "rolesPlusPlus": [22, 26, 31, 33]
  },
  {
    "resourceId": 266260,
    "assetId": 266260,
    "preferredPosition": "CB",
    "possiblePositions": ["CB", "CDM"],
    "rating": 66,
    "metalId": 2,
    "preferredFoot": "Right",
    "skillMoves": 2,
    "playStyles": [],
    "playStylesPlus": [],
    "eaRolesPlus": [13],
    "eaRolesPlusPlus": [],
    "clubId": 819,
    "leagueId": 1,
    "countryId": 163,
    "weakFoot": 4,
    "attributes": [73, 44, 59, 59, 66, 65],
    "metaRating": 63.31930529546359,
    "playerRoleId": 12,
    "canEvolve": true,
    "hasDynamicImage": false,
    "playerUrl": "https://assets.easysbc.io/fc26/players/266260.png",
    "newPlayer": false,
    "versionId": 1,
    "eaPlayerId": null,
    "untradeable": false,
    "owned": false,
    "name": "Junnosuke Suzuki",
    "cardName": "Suzuki",
    "price": 350,
    "rolesPlus": [13],
    "rolesPlusPlus": [13]
  },
  {
    "resourceId": 254211,
    "assetId": 254211,
    "preferredPosition": "RB",
    "possiblePositions": ["RB", "RM"],
    "rating": 67,
    "metalId": 2,
    "preferredFoot": "Right",
    "skillMoves": 2,
    "playStyles": [],
    "playStylesPlus": [],
    "eaRolesPlus": [5, 25],
    "eaRolesPlusPlus": [],
    "clubId": 111339,
    "leagueId": 68,
    "countryId": 57,
    "weakFoot": 2,
    "attributes": [74, 45, 60, 65, 64, 73],
    "metaRating": 63.31897110286066,
    "playerRoleId": 3,
    "canEvolve": true,
    "hasDynamicImage": false,
    "playerUrl": "https://assets.easysbc.io/fc26/players/254211.png",
    "newPlayer": false,
    "versionId": 0,
    "eaPlayerId": null,
    "untradeable": false,
    "owned": false,
    "name": "Jhon Espinoza",
    "cardName": "Espinoza",
    "price": 200,
    "rolesPlus": [5, 25],
    "rolesPlusPlus": [5, 25]
  },
  {
    "resourceId": 242541,
    "assetId": 242541,
    "preferredPosition": "CB",
    "possiblePositions": ["CB", "LB"],
    "rating": 70,
    "metalId": 2,
    "preferredFoot": "Left",
    "skillMoves": 2,
    "playStyles": [10, 27],
    "playStylesPlus": [],
    "eaRolesPlus": [8, 11, 12],
    "eaRolesPlusPlus": [],
    "clubId": 1951,
    "leagueId": 14,
    "countryId": 35,
    "weakFoot": 2,
    "attributes": [65, 46, 56, 61, 70, 75],
    "metaRating": 63.31784796334046,
    "playerRoleId": 11,
    "canEvolve": true,
    "hasDynamicImage": false,
    "playerUrl": "https://assets.easysbc.io/fc26/players/242541.png",
    "newPlayer": false,
    "versionId": 0,
    "eaPlayerId": null,
    "untradeable": false,
    "owned": false,
    "name": "Ciaron Brown",
    "cardName": "Brown",
    "price": 200,
    "rolesPlus": [8, 11, 12],
    "rolesPlusPlus": [8, 11, 12]
  },
  {
    "resourceId": 205895,
    "assetId": 205895,
    "preferredPosition": "CDM",
    "possiblePositions": ["CAM", "CDM", "CM"],
    "rating": 70,
    "metalId": 2,
    "preferredFoot": "Right",
    "skillMoves": 2,
    "playStyles": [10, 14, 18],
    "playStylesPlus": [],
    "eaRolesPlus": [14],
    "eaRolesPlusPlus": [],
    "clubId": 100325,
    "leagueId": 322,
    "countryId": 17,
    "weakFoot": 3,
    "attributes": [67, 66, 67, 69, 67, 73],
    "metaRating": 63.31627106605818,
    "playerRoleId": 14,
    "canEvolve": true,
    "hasDynamicImage": false,
    "playerUrl": "https://assets.easysbc.io/fc26/players/205895.png",
    "newPlayer": false,
    "versionId": 0,
    "eaPlayerId": null,
    "untradeable": false,
    "owned": false,
    "name": "Alexander Ring",
    "cardName": "Ring",
    "price": 200,
    "rolesPlus": [14],
    "rolesPlusPlus": [14]
  },
  {
    "resourceId": 263790,
    "assetId": 263790,
    "preferredPosition": "LM",
    "possiblePositions": ["CAM", "LM", "LW"],
    "rating": 66,
    "metalId": 2,
    "preferredFoot": "Left",
    "skillMoves": 4,
    "playStyles": [21],
    "playStylesPlus": [],
    "eaRolesPlus": [27, 30, 33],
    "eaRolesPlusPlus": [],
    "clubId": 717,
    "leagueId": 308,
    "countryId": 54,
    "weakFoot": 3,
    "attributes": [87, 64, 52, 74, 28, 47],
    "metaRating": 63.31551366167367,
    "playerRoleId": 30,
    "canEvolve": true,
    "hasDynamicImage": false,
    "playerUrl": "https://assets.easysbc.io/fc26/players/263790.png",
    "newPlayer": false,
    "versionId": 1,
    "eaPlayerId": null,
    "untradeable": false,
    "owned": false,
    "name": "L\u00e9o Ch\u00fa",
    "cardName": "L\u00e9o Ch\u00fa",
    "price": 850,
    "rolesPlus": [27, 30, 33],
    "rolesPlusPlus": [27, 30, 33]
  },
  {
    "resourceId": 222493,
    "assetId": 222493,
    "preferredPosition": "CB",
    "possiblePositions": ["CB"],
    "rating": 74,
    "metalId": 2,
    "preferredFoot": "Right",
    "skillMoves": 2,
    "playStyles": [17],
    "playStylesPlus": [],
    "eaRolesPlus": [11, 48],
    "eaRolesPlusPlus": [],
    "clubId": 23,
    "leagueId": 19,
    "countryId": 21,
    "weakFoot": 2,
    "attributes": [58, 41, 54, 50, 76, 72],
    "metaRating": 63.313288136186195,
    "playerRoleId": 11,
    "canEvolve": true,
    "hasDynamicImage": false,
    "playerUrl": "https://assets.easysbc.io/fc26/players/222493.png",
    "newPlayer": false,
    "versionId": 1,
    "eaPlayerId": null,
    "untradeable": false,
    "owned": false,
    "name": "Marvin Friedrich",
    "cardName": "Friedrich",
    "price": 350,
    "rolesPlus": [11, 48],
    "rolesPlusPlus": [11, 48]
  },
  {
    "resourceId": 266256,
    "assetId": 266256,
    "preferredPosition": "ST",
    "possiblePositions": ["ST"],
    "rating": 73,
    "metalId": 2,
    "preferredFoot": "Right",
    "skillMoves": 3,
    "playStyles": [0, 29],
    "playStylesPlus": [],
    "eaRolesPlus": [42, 44],
    "eaRolesPlusPlus": [],
    "clubId": 481,
    "leagueId": 53,
    "countryId": 133,
    "weakFoot": 3,
    "attributes": [77, 72, 56, 70, 29, 75],
    "metaRating": 63.313118095010694,
    "playerRoleId": 44,
    "canEvolve": true,
    "hasDynamicImage": false,
    "playerUrl": "https://assets.easysbc.io/fc26/players/266256.png",
    "newPlayer": false,
    "versionId": 0,
    "eaPlayerId": null,
    "untradeable": false,
    "owned": false,
    "name": "Akor Jerome Adams",
    "cardName": "Adams",
    "price": 200,
    "rolesPlus": [42, 44],
    "rolesPlusPlus": [42, 44]
  },
  {
    "resourceId": 211999,
    "assetId": 211999,
    "preferredPosition": "CDM",
    "possiblePositions": ["CDM", "CM"],
    "rating": 75,
    "metalId": 3,
    "preferredFoot": "Right",
    "skillMoves": 2,
    "playStyles": [19, 28],
    "playStylesPlus": [],
    "eaRolesPlus": [14, 17, 18],
    "eaRolesPlusPlus": [],
    "clubId": 1831,
    "leagueId": 19,
    "countryId": 21,
    "weakFoot": 3,
    "attributes": [57, 43, 57, 62, 79, 83],
    "metaRating": 63.31235073945808,
    "playerRoleId": 14,
    "canEvolve": true,
    "hasDynamicImage": false,
    "playerUrl": "https://assets.easysbc.io/fc26/players/211999.png",
    "newPlayer": false,
    "versionId": 0,
    "eaPlayerId": null,
    "untradeable": false,
    "owned": false,
    "name": "Rani Khedira",
    "cardName": "Khedira",
    "price": 350,
    "rolesPlus": [14, 17, 18],
    "rolesPlusPlus": [14, 17, 18]
  },
  {
    "resourceId": 260474,
    "assetId": 260474,
    "preferredPosition": "CDM",
    "possiblePositions": ["CB", "CDM", "CM"],
    "rating": 72,
    "metalId": 2,
    "preferredFoot": "Right",
    "skillMoves": 2,
    "playStyles": [10, 14, 26, 28, 8],
    "playStylesPlus": [],
    "eaRolesPlus": [13, 15, 16, 18],
    "eaRolesPlusPlus": [],
    "clubId": 980,
    "leagueId": 83,
    "countryId": 167,
    "weakFoot": 2,
    "attributes": [67, 58, 63, 65, 68, 79],
    "metaRating": 63.311700094686735,
    "playerRoleId": 16,
    "canEvolve": true,
    "hasDynamicImage": false,
    "playerUrl": "https://assets.easysbc.io/fc26/players/260474.png",
    "newPlayer": false,
    "versionId": 1,
    "eaPlayerId": null,
    "untradeable": false,
    "owned": false,
    "name": "Kim Bong Soo",
    "cardName": "Kim Bong Soo",
    "price": 350,
    "rolesPlus": [13, 15, 16, 18],
    "rolesPlusPlus": [13, 15, 16, 18]
  },
  {
    "resourceId": 209504,
    "assetId": 209504,
    "preferredPosition": "CAM",
    "possiblePositions": ["CAM", "CM", "ST"],
    "rating": 71,
    "metalId": 2,
    "preferredFoot": "Left",
    "skillMoves": 3,
    "playStyles": [0, 1, 20, 22, 7, 8],
    "playStylesPlus": [],
    "eaRolesPlus": [33, 34, 43],
    "eaRolesPlusPlus": [],
    "clubId": 165,
    "leagueId": 20,
    "countryId": 46,
    "weakFoot": 4,
    "attributes": [70, 73, 65, 74, 25, 67],
    "metaRating": 63.311640712578466,
    "playerRoleId": 32,
    "canEvolve": true,
    "hasDynamicImage": false,
    "playerUrl": "https://assets.easysbc.io/fc26/players/209504.png",
    "newPlayer": false,
    "versionId": 1,
    "eaPlayerId": null,
    "untradeable": false,
    "owned": false,
    "name": "Branimir Hrgota",
    "cardName": "Hrgota",
    "price": 350,
    "rolesPlus": [33, 34, 43],
    "rolesPlusPlus": [33, 34, 43]
  },
  {
    "resourceId": 250946,
    "assetId": 250946,
    "preferredPosition": "LM",
    "possiblePositions": ["CAM", "LM", "LW"],
    "rating": 68,
    "metalId": 2,
    "preferredFoot": "Right",
    "skillMoves": 3,
    "playStyles": [13, 20],
    "playStylesPlus": [],
    "eaRolesPlus": [27, 29, 33],
    "eaRolesPlusPlus": [],
    "clubId": 485,
    "leagueId": 20,
    "countryId": 21,
    "weakFoot": 4,
    "attributes": [81, 61, 61, 67, 46, 65],
    "metaRating": 63.31079351048053,
    "playerRoleId": 28,
    "canEvolve": true,
    "hasDynamicImage": false,
    "playerUrl": "https://assets.easysbc.io/fc26/players/250946.png",
    "newPlayer": false,
    "versionId": 0,
    "eaPlayerId": null,
    "untradeable": false,
    "owned": false,
    "name": "Jannik Rochelt",
    "cardName": "Rochelt",
    "price": 200,
    "rolesPlus": [27, 29, 33],
    "rolesPlusPlus": [27, 29, 33]
  },
  {
    "resourceId": 246987,
    "assetId": 246987,
    "preferredPosition": "GK",
    "possiblePositions": ["GK"],
    "rating": 67,
    "metalId": 2,
    "preferredFoot": "Right",
    "skillMoves": 1,
    "playStyles": [30],
    "playStylesPlus": [],
    "eaRolesPlus": [1],
    "eaRolesPlusPlus": [],
    "clubId": 834,
    "leagueId": 65,
    "countryId": 25,
    "weakFoot": 2,
    "attributes": [66, 65, 62, 69, 32, 66],
    "metaRating": 63.30708353057618,
    "playerRoleId": 1,
    "canEvolve": true,
    "hasDynamicImage": false,
    "playerUrl": "https://assets.easysbc.io/fc26/players/246987.png",
    "newPlayer": false,
    "versionId": 0,
    "eaPlayerId": null,
    "untradeable": false,
    "owned": false,
    "name": "Conor Kearns",
    "cardName": "Kearns",
    "price": 200,
    "rolesPlus": [1],
    "rolesPlusPlus": [1]
  },
  {
    "resourceId": 263227,
    "assetId": 263227,
    "preferredPosition": "LW",
    "possiblePositions": ["CM", "LM", "LW"],
    "rating": 74,
    "metalId": 2,
    "preferredFoot": "Right",
    "skillMoves": 3,
    "playStyles": [],
    "playStylesPlus": [],
    "eaRolesPlus": [22, 38],
    "eaRolesPlusPlus": [],
    "clubId": 450,
    "leagueId": 53,
    "countryId": 46,
    "weakFoot": 3,
    "attributes": [74, 69, 71, 76, 61, 62],
    "metaRating": 63.30663063209587,
    "playerRoleId": 28,
    "canEvolve": true,
    "hasDynamicImage": false,
    "playerUrl": "https://assets.easysbc.io/fc26/players/263227.png",
    "newPlayer": false,
    "versionId": 1,
    "eaPlayerId": null,
    "untradeable": false,
    "owned": false,
    "name": "Williot Swedberg",
    "cardName": "Swedberg",
    "price": 350,
    "rolesPlus": [22, 38],
    "rolesPlusPlus": [22, 38]
  },
  {
    "resourceId": 204931,
    "assetId": 204931,
    "preferredPosition": "GK",
    "possiblePositions": ["GK"],
    "rating": 66,
    "metalId": 2,
    "preferredFoot": "Right",
    "skillMoves": 1,
    "playStyles": [],
    "playStylesPlus": [],
    "eaRolesPlus": [1],
    "eaRolesPlusPlus": [],
    "clubId": 111393,
    "leagueId": 351,
    "countryId": 34,
    "weakFoot": 1,
    "attributes": [67, 64, 66, 68, 56, 65],
    "metaRating": 63.306311725016194,
    "playerRoleId": 1,
    "canEvolve": true,
    "hasDynamicImage": false,
    "playerUrl": "https://assets.easysbc.io/fc26/players/204931.png",
    "newPlayer": false,
    "versionId": 0,
    "eaPlayerId": null,
    "untradeable": false,
    "owned": false,
    "name": "Joshua Smits",
    "cardName": "Smits",
    "price": 200,
    "rolesPlus": [1],
    "rolesPlusPlus": [1]
  },
  {
    "resourceId": 225106,
    "assetId": 225106,
    "preferredPosition": "CB",
    "possiblePositions": ["CB"],
    "rating": 71,
    "metalId": 2,
    "preferredFoot": "Right",
    "skillMoves": 2,
    "playStyles": [18],
    "playStylesPlus": [],
    "eaRolesPlus": [11, 12],
    "eaRolesPlusPlus": [],
    "clubId": 100888,
    "leagueId": 54,
    "countryId": 45,
    "weakFoot": 3,
    "attributes": [62, 41, 56, 61, 71, 77],
    "metaRating": 63.30539116741171,
    "playerRoleId": 12,
    "canEvolve": true,
    "hasDynamicImage": false,
    "playerUrl": "https://assets.easysbc.io/fc26/players/225106.png",
    "newPlayer": false,
    "versionId": 0,
    "eaPlayerId": null,
    "untradeable": false,
    "owned": false,
    "name": "Jorge S\u00e1enz",
    "cardName": "Jorge S\u00e1enz",
    "price": 200,
    "rolesPlus": [11, 12],
    "rolesPlusPlus": [11, 12]
  }
]
