[
  {
    "resourceId": 272723,
    "assetId": 272723,
    "preferredPosition": "CB",
    "possiblePositions": ["CB", "RB"],
    "rating": 66,
    "metalId": 2,
    "preferredFoot": "Right",
    "skillMoves": 2,
    "playStyles": [],
    "playStylesPlus": [],
    "eaRolesPlus": [4, 12, 48],
    "eaRolesPlusPlus": [],
    "clubId": 1877,
    "leagueId": 353,
    "countryId": 52,
    "weakFoot": 3,
    "attributes": [63, 30, 37, 43, 65, 79],
    "metaRating": 60.45257987605228,
    "playerRoleId": 12,
    "canEvolve": true,
    "hasDynamicImage": false,
    "playerUrl": "https://assets.easysbc.io/fc26/players/272723.png",
    "newPlayer": false,
    "versionId": 0,
    "eaPlayerId": null,
    "untradeable": false,
    "owned": false,
    "name": "Lautaro Di Lollo",
    "cardName": "Di Lollo",
    "price": 200,
    "rolesPlus": [4, 12, 48],
    "rolesPlusPlus": [4, 12, 48]
  },
  {
    "resourceId": 173165,
    "assetId": 173165,
    "preferredPosition": "GK",
    "possiblePositions": ["GK"],
    "rating": 66,
    "metalId": 2,
    "preferredFoot": "Right",
    "skillMoves": 1,
    "playStyles": [],
    "playStylesPlus": [],
    "eaRolesPlus": [1],
    "eaRolesPlusPlus": [],
    "clubId": 1837,
    "leagueId": 32,
    "countryId": 27,
    "weakFoot": 2,
    "attributes": [64, 64, 61, 68, 30, 65],
    "metaRating": 60.45254784109701,
    "playerRoleId": 1,
    "canEvolve": true,
    "hasDynamicImage": false,
    "playerUrl": "https://assets.easysbc.io/fc26/players/173165.png",
    "newPlayer": false,
    "versionId": 0,
    "eaPlayerId": null,
    "untradeable": false,
    "owned": false,
    "name": "Nicola Ravaglia",
    "cardName": "Ravaglia",
    "price": 200,
    "rolesPlus": [1],
    "rolesPlusPlus": [1]
  },
  {
    "resourceId": 275206,
    "assetId": 275206,
    "preferredPosition": "RB",
    "possiblePositions": ["CB", "CDM", "RB", "RM"],
    "rating": 62,
    "metalId": 1,
    "preferredFoot": "Right",
    "skillMoves": 2,
    "playStyles": [],
    "playStylesPlus": [],
    "eaRolesPlus": [3],
    "eaRolesPlusPlus": [],
    "clubId": 894,
    "leagueId": 189,
    "countryId": 85,
    "weakFoot": 3,
    "attributes": [74, 43, 55, 61, 57, 61],
    "metaRating": 60.451885698469695,
    "playerRoleId": 3,
    "canEvolve": true,
    "hasDynamicImage": false,
    "playerUrl": "https://assets.easysbc.io/fc26/players/275206.png",
    "newPlayer": false,
    "versionId": 0,
    "eaPlayerId": null,
    "untradeable": false,
    "owned": false,
    "name": "Livano Comenencia",
    "cardName": "Comenencia",
    "price": 200,
    "rolesPlus": [3],
    "rolesPlusPlus": [3]
  },
  {
    "resourceId": 216627,
    "assetId": 216627,
    "preferredPosition": "ST",
    "possiblePositions": ["ST"],
    "rating": 72,
    "metalId": 2,
    "preferredFoot": "Right",
    "skillMoves": 3,
    "playStyles": [19, 29, 4],
    "playStylesPlus": [],
    "eaRolesPlus": [42, 44],
    "eaRolesPlusPlus": [],
    "clubId": 1947,
    "leagueId": 14,
    "countryId": 50,
    "weakFoot": 3,
    "attributes": [61, 69, 56, 65, 46, 79],
    "metaRating": 60.45117254149081,
    "playerRoleId": 44,
    "canEvolve": true,
    "hasDynamicImage": false,
    "playerUrl": "https://assets.easysbc.io/fc26/players/216627.png",
    "newPlayer": false,
    "versionId": 0,
    "eaPlayerId": null,
    "untradeable": false,
    "owned": false,
    "name": "Kieffer Moore",
    "cardName": "Moore",
    "price": 200,
    "rolesPlus": [42, 44],
    "rolesPlusPlus": [42, 44]
  },
  {
    "resourceId": 255607,
    "assetId": 255607,
    "preferredPosition": "RB",
    "possiblePositions": ["RB"],
    "rating": 69,
    "metalId": 2,
    "preferredFoot": "Right",
    "skillMoves": 2,
    "playStyles": [],
    "playStylesPlus": [],
    "eaRolesPlus": [4, 5, 46],
    "eaRolesPlusPlus": [],
    "clubId": 110396,
    "leagueId": 353,
    "countryId": 56,
    "weakFoot": 2,
    "attributes": [68, 41, 58, 58, 67, 74],
    "metaRating": 60.45085463988573,
    "playerRoleId": 3,
    "canEvolve": true,
    "hasDynamicImage": false,
    "playerUrl": "https://assets.easysbc.io/fc26/players/255607.png",
    "newPlayer": false,
    "versionId": 0,
    "eaPlayerId": null,
    "untradeable": false,
    "owned": false,
    "name": "Jherson Mosquera",
    "cardName": "Mosquera",
    "price": 200,
    "rolesPlus": [4, 5, 46],
    "rolesPlusPlus": [4, 5, 46]
  },
  {
    "resourceId": 262394,
    "assetId": 262394,
    "preferredPosition": "CB",
    "possiblePositions": ["CB"],
    "rating": 78,
    "metalId": 3,
    "preferredFoot": "Right",
    "skillMoves": 2,
    "playStyles": [10, 15],
    "playStylesPlus": [],
    "eaRolesPlus": [11, 12, 13],
    "eaRolesPlusPlus": [],
    "clubId": 48,
    "leagueId": 31,
    "countryId": 34,
    "weakFoot": 3,
    "attributes": [49, 55, 61, 62, 80, 76],
    "metaRating": 60.447624349827024,
    "playerRoleId": 11,
    "canEvolve": true,
    "hasDynamicImage": false,
    "playerUrl": "https://assets.easysbc.io/fc26/players/262394.png",
    "newPlayer": false,
    "versionId": 0,
    "eaPlayerId": null,
    "untradeable": false,
    "owned": false,
    "name": "Sam Beukema",
    "cardName": "Beukema",
    "price": 350,
    "rolesPlus": [11, 12, 13],
    "rolesPlusPlus": [11, 12, 13]
  },
  {
    "resourceId": 267782,
    "assetId": 267782,
    "preferredPosition": "ST",
    "possiblePositions": ["CAM", "RM", "ST"],
    "rating": 66,
    "metalId": 2,
    "preferredFoot": "Right",
    "skillMoves": 3,
    "playStyles": [],
    "playStylesPlus": [],
    "eaRolesPlus": [26, 41, 43],
    "eaRolesPlusPlus": [],
    "clubId": 580,
    "leagueId": 20,
    "countryId": 21,
    "weakFoot": 4,
    "attributes": [75, 65, 60, 71, 29, 56],
    "metaRating": 60.446406308215614,
    "playerRoleId": 26,
    "canEvolve": true,
    "hasDynamicImage": false,
    "playerUrl": "https://assets.easysbc.io/fc26/players/267782.png",
    "newPlayer": false,
    "versionId": 0,
    "eaPlayerId": null,
    "untradeable": false,
    "owned": false,
    "name": "Bambas\u00e9 Cont\u00e9",
    "cardName": "Cont\u00e9",
    "price": 200,
    "rolesPlus": [26, 41, 43],
    "rolesPlusPlus": [26, 41, 43]
  },
  {
    "resourceId": 74063,
    "assetId": 74063,
    "preferredPosition": "CB",
    "possiblePositions": ["CB", "RB", "RM"],
    "rating": 67,
    "metalId": 2,
    "preferredFoot": "Right",
    "skillMoves": 2,
    "playStyles": [],
    "playStylesPlus": [],
    "eaRolesPlus": [5, 11, 48],
    "eaRolesPlusPlus": [],
    "clubId": 111138,
    "leagueId": 39,
    "countryId": 56,
    "weakFoot": 2,
    "attributes": [64, 41, 59, 59, 69, 71],
    "metaRating": 60.445410453919564,
    "playerRoleId": 11,
    "canEvolve": true,
    "hasDynamicImage": false,
    "playerUrl": "https://assets.easysbc.io/fc26/players/74063.png",
    "newPlayer": false,
    "versionId": 0,
    "eaPlayerId": null,
    "untradeable": false,
    "owned": false,
    "name": "Jefferson D\u00edaz",
    "cardName": "D\u00edaz",
    "price": 200,
    "rolesPlus": [5, 11, 48],
    "rolesPlusPlus": [5, 11, 48]
  },
  {
    "resourceId": 265269,
    "assetId": 265269,
    "preferredPosition": "GK",
    "possiblePositions": ["GK"],
    "rating": 68,
    "metalId": 2,
    "preferredFoot": "Right",
    "skillMoves": 1,
    "playStyles": [],
    "playStylesPlus": [],
    "eaRolesPlus": [1],
    "eaRolesPlusPlus": [],
    "clubId": 116016,
    "leagueId": 2216,
    "countryId": 14,
    "weakFoot": 3,
    "attributes": [68, 68, 70, 67, 35, 66],
    "metaRating": 60.44520845334853,
    "playerRoleId": 1,
    "canEvolve": true,
    "hasDynamicImage": false,
    "playerUrl": "https://assets.easysbc.io/fc26/players/265269.png",
    "newPlayer": false,
    "versionId": 0,
    "eaPlayerId": null,
    "untradeable": false,
    "owned": false,
    "name": "Emily Ramsey",
    "cardName": "Ramsey",
    "price": 200,
    "rolesPlus": [1],
    "rolesPlusPlus": [1]
  },
  {
    "resourceId": 272783,
    "assetId": 272783,
    "preferredPosition": "CM",
    "possiblePositions": ["CAM", "CM", "RM"],
    "rating": 69,
    "metalId": 2,
    "preferredFoot": "Right",
    "skillMoves": 3,
    "playStyles": [],
    "playStylesPlus": [],
    "eaRolesPlus": [22, 26],
    "eaRolesPlusPlus": [],
    "clubId": 55,
    "leagueId": 31,
    "countryId": 18,
    "weakFoot": 3,
    "attributes": [72, 59, 66, 71, 62, 69],
    "metaRating": 60.44506467985933,
    "playerRoleId": 20,
    "canEvolve": true,
    "hasDynamicImage": false,
    "playerUrl": "https://assets.easysbc.io/fc26/players/272783.png",
    "newPlayer": false,
    "versionId": 0,
    "eaPlayerId": null,
    "untradeable": false,
    "owned": false,
    "name": "Arthur Atta",
    "cardName": "Atta",
    "price": 200,
    "rolesPlus": [22, 26],
    "rolesPlusPlus": [22, 26]
  },
  {
    "resourceId": 219452,
    "assetId": 219452,
    "preferredPosition": "CDM",
    "possiblePositions": ["CDM", "CM"],
    "rating": 69,
    "metalId": 2,
    "preferredFoot": "Right",
    "skillMoves": 2,
    "playStyles": [],
    "playStylesPlus": [],
    "eaRolesPlus": [14, 15, 19],
    "eaRolesPlusPlus": [],
    "clubId": 111328,
    "leagueId": 1014,
    "countryId": 52,
    "weakFoot": 3,
    "attributes": [67, 54, 60, 66, 67, 75],
    "metaRating": 60.443035559929015,
    "playerRoleId": 14,
    "canEvolve": true,
    "hasDynamicImage": false,
    "playerUrl": "https://assets.easysbc.io/fc26/players/219452.png",
    "newPlayer": false,
    "versionId": 0,
    "eaPlayerId": null,
    "untradeable": false,
    "owned": false,
    "name": "Juli\u00e1n Fern\u00e1ndez",
    "cardName": "Fern\u00e1ndez",
    "price": 200,
    "rolesPlus": [14, 15, 19],
    "rolesPlusPlus": [14, 15, 19]
  },
  {
    "resourceId": 269921,
    "assetId": 269921,
    "preferredPosition": "GK",
    "possiblePositions": ["GK"],
    "rating": 74,
    "metalId": 2,
    "preferredFoot": "Left",
    "skillMoves": 1,
    "playStyles": [],
    "playStylesPlus": [],
    "eaRolesPlus": [1],
    "eaRolesPlusPlus": [],
    "clubId": 131733,
    "leagueId": 2222,
    "countryId": 18,
    "weakFoot": 3,
    "attributes": [75, 74, 74, 72, 47, 72],
    "metaRating": 60.44217251713253,
    "playerRoleId": 1,
    "canEvolve": true,
    "hasDynamicImage": false,
    "playerUrl": "https://assets.easysbc.io/fc26/players/269921.png",
    "newPlayer": false,
    "versionId": 1,
    "eaPlayerId": null,
    "untradeable": false,
    "owned": false,
    "name": "Romane Salvador",
    "cardName": "Salvador",
    "price": 350,
    "rolesPlus": [1],
    "rolesPlusPlus": [1]
  },
  {
    "resourceId": 240580,
    "assetId": 240580,
    "preferredPosition": "LM",
    "possiblePositions": ["LM", "LW", "RM"],
    "rating": 62,
    "metalId": 1,
    "preferredFoot": "Right",
    "skillMoves": 3,
    "playStyles": [20, 6],
    "playStylesPlus": [],
    "eaRolesPlus": [23, 27, 29],
    "eaRolesPlusPlus": [],
    "clubId": 111393,
    "leagueId": 351,
    "countryId": 195,
    "weakFoot": 4,
    "attributes": [81, 53, 54, 66, 25, 66],
    "metaRating": 60.4408905596914,
    "playerRoleId": 28,
    "canEvolve": true,
    "hasDynamicImage": false,
    "playerUrl": "https://assets.easysbc.io/fc26/players/240580.png",
    "newPlayer": false,
    "versionId": 0,
    "eaPlayerId": null,
    "untradeable": false,
    "owned": false,
    "name": "Ben Folami",
    "cardName": "Folami",
    "price": 200,
    "rolesPlus": [23, 27, 29],
    "rolesPlusPlus": [23, 27, 29]
  },
  {
    "resourceId": 275317,
    "assetId": 275317,
    "preferredPosition": "GK",
    "possiblePositions": ["GK"],
    "rating": 64,
    "metalId": 1,
    "preferredFoot": "Right",
    "skillMoves": 1,
    "playStyles": [],
    "playStylesPlus": [],
    "eaRolesPlus": [1],
    "eaRolesPlusPlus": [],
    "clubId": 66,
    "leagueId": 16,
    "countryId": 18,
    "weakFoot": 3,
    "attributes": [65, 61, 57, 67, 19, 62],
    "metaRating": 60.43914935244189,
    "playerRoleId": 1,
    "canEvolve": true,
    "hasDynamicImage": false,
    "playerUrl": "https://assets.easysbc.io/fc26/players/275317.png",
    "newPlayer": false,
    "versionId": 0,
    "eaPlayerId": null,
    "untradeable": false,
    "owned": false,
    "name": "Mathieu Patouillet",
    "cardName": "Patouillet",
    "price": 0,
    "rolesPlus": [1],
    "rolesPlusPlus": [1]
  },
  {
    "resourceId": 275733,
    "assetId": 275733,
    "preferredPosition": "GK",
    "possiblePositions": ["GK"],
    "rating": 65,
    "metalId": 2,
    "preferredFoot": "Right",
    "skillMoves": 1,
    "playStyles": [],
    "playStylesPlus": [],
    "eaRolesPlus": [1],
    "eaRolesPlusPlus": [],
    "clubId": 1715,
    "leagueId": 189,
    "countryId": 47,
    "weakFoot": 2,
    "attributes": [69, 62, 64, 68, 30, 60],
    "metaRating": 60.43820446570837,
    "playerRoleId": 1,
    "canEvolve": true,
    "hasDynamicImage": false,
    "playerUrl": "https://assets.easysbc.io/fc26/players/275733.png",
    "newPlayer": false,
    "versionId": 0,
    "eaPlayerId": null,
    "untradeable": false,
    "owned": false,
    "name": "Niklas Steffen",
    "cardName": "Steffen",
    "price": 200,
    "rolesPlus": [1],
    "rolesPlusPlus": [1]
  },
  {
    "resourceId": 76214,
    "assetId": 76214,
    "preferredPosition": "RM",
    "possiblePositions": ["RM", "RW"],
    "rating": 70,
    "metalId": 2,
    "preferredFoot": "Right",
    "skillMoves": 3,
    "playStyles": [],
    "playStylesPlus": [],
    "eaRolesPlus": [23],
    "eaRolesPlusPlus": [],
    "clubId": 131477,
    "leagueId": 2221,
    "countryId": 95,
    "weakFoot": 3,
    "attributes": [80, 67, 65, 68, 43, 67],
    "metaRating": 60.43774541283613,
    "playerRoleId": 24,
    "canEvolve": true,
    "hasDynamicImage": false,
    "playerUrl": "https://assets.easysbc.io/fc26/players/76214.png",
    "newPlayer": false,
    "versionId": 0,
    "eaPlayerId": null,
    "untradeable": false,
    "owned": false,
    "name": "Karlie Lema",
    "cardName": "Lema",
    "price": 200,
    "rolesPlus": [23],
    "rolesPlusPlus": [23]
  },
  {
    "resourceId": 224956,
    "assetId": 224956,
    "preferredPosition": "CAM",
    "possiblePositions": ["CAM", "CM"],
    "rating": 65,
    "metalId": 2,
    "preferredFoot": "Right",
    "skillMoves": 3,
    "playStyles": [13, 20, 8],
    "playStylesPlus": [],
    "eaRolesPlus": [22, 31],
    "eaRolesPlusPlus": [],
    "clubId": 1798,
    "leagueId": 61,
    "countryId": 14,
    "weakFoot": 3,
    "attributes": [77, 61, 65, 68, 47, 52],
    "metaRating": 60.43712722478766,
    "playerRoleId": 31,
    "canEvolve": true,
    "hasDynamicImage": false,
    "playerUrl": "https://assets.easysbc.io/fc26/players/224956.png",
    "newPlayer": false,
    "versionId": 1,
    "eaPlayerId": null,
    "untradeable": false,
    "owned": false,
    "name": "Daniel Crowley",
    "cardName": "Crowley",
    "price": 350,
    "rolesPlus": [22, 31],
    "rolesPlusPlus": [22, 31]
  },
  {
    "resourceId": 267973,
    "assetId": 267973,
    "preferredPosition": "CM",
    "possiblePositions": ["CAM", "CM", "ST"],
    "rating": 71,
    "metalId": 2,
    "preferredFoot": "Right",
    "skillMoves": 3,
    "playStyles": [13, 3, 8],
    "playStylesPlus": [],
    "eaRolesPlus": [18, 22, 33, 43],
    "eaRolesPlusPlus": [],
    "clubId": 111276,
    "leagueId": 17,
    "countryId": 18,
    "weakFoot": 3,
    "attributes": [68, 67, 71, 73, 54, 55],
    "metaRating": 60.4356330491347,
    "playerRoleId": 31,
    "canEvolve": true,
    "hasDynamicImage": false,
    "playerUrl": "https://assets.easysbc.io/fc26/players/267973.png",
    "newPlayer": false,
    "versionId": 0,
    "eaPlayerId": null,
    "untradeable": false,
    "owned": false,
    "name": "Enzo Bardeli",
    "cardName": "Bardeli",
    "price": 200,
    "rolesPlus": [18, 22, 33, 43],
    "rolesPlusPlus": [18, 22, 33, 43]
  },
  {
    "resourceId": 264966,
    "assetId": 264966,
    "preferredPosition": "GK",
    "possiblePositions": ["GK"],
    "rating": 70,
    "metalId": 2,
    "preferredFoot": "Right",
    "skillMoves": 1,
    "playStyles": [],
    "playStylesPlus": [],
    "eaRolesPlus": [2],
    "eaRolesPlusPlus": [],
    "clubId": 116005,
    "leagueId": 2215,
    "countryId": 21,
    "weakFoot": 3,
    "attributes": [70, 68, 72, 69, 40, 71],
    "metaRating": 60.43537552445709,
    "playerRoleId": 1,
    "canEvolve": true,
    "hasDynamicImage": false,
    "playerUrl": "https://assets.easysbc.io/fc26/players/264966.png",
    "newPlayer": false,
    "versionId": 0,
    "eaPlayerId": null,
    "untradeable": false,
    "owned": false,
    "name": "Julia Kassen",
    "cardName": "Kassen",
    "price": 200,
    "rolesPlus": [2],
    "rolesPlusPlus": [2]
  },
  {
    "resourceId": 237715,
    "assetId": 237715,
    "preferredPosition": "ST",
    "possiblePositions": ["ST"],
    "rating": 75,
    "metalId": 3,
    "preferredFoot": "Right",
    "skillMoves": 3,
    "playStyles": [],
    "playStylesPlus": [],
    "eaRolesPlus": [41],
    "eaRolesPlusPlus": [],
    "clubId": 1745,
    "leagueId": 31,
    "countryId": 27,
    "weakFoot": 3,
    "attributes": [73, 74, 64, 76, 29, 69],
    "metaRating": 60.43380895639308,
    "playerRoleId": 41,
    "canEvolve": true,
    "hasDynamicImage": false,
    "playerUrl": "https://assets.easysbc.io/fc26/players/237715.png",
    "newPlayer": false,
    "versionId": 0,
    "eaPlayerId": null,
    "untradeable": false,
    "owned": false,
    "name": "Patrick Cutrone",
    "cardName": "Cutrone",
    "price": 0,
    "rolesPlus": [41],
    "rolesPlusPlus": [41]
  }
]
