[
  {
    "resourceId": 77466,
    "assetId": 77466,
    "preferredPosition": "ST",
    "possiblePositions": ["ST"],
    "rating": 52,
    "preferredFoot": "Right",
    "skillMoves": 2,
    "playStyles": [],
    "playStylesPlus": [],
    "eaRolesPlus": [41],
    "eaRolesPlusPlus": [],
    "metalId": 1,
    "clubId": 693,
    "leagueId": 39,
    "countryId": 95,
    "weakFoot": 3,
    "attributes": [61, 52, 38, 48, 23, 55],
    "metaRating": 37.99503655528261,
    "playerRoleId": 41,
    "canEvolve": true,
    "hasDynamicImage": false,
    "playerUrl": "https://assets.easysbc.io/fc26/players/77466.png",
    "newPlayer": false,
    "versionId": 0,
    "eaPlayerId": null,
    "untradeable": false,
    "owned": false,
    "name": "Dean Boltz",
    "cardName": "Boltz",
    "price": 200,
    "rolesPlus": [41],
    "rolesPlusPlus": [41]
  },
  {
    "resourceId": 231747,
    "assetId": 231747,
    "preferredPosition": "ST",
    "possiblePositions": ["LM", "LW", "ST"],
    "rating": 91,
    "metalId": 3,
    "preferredFoot": "Right",
    "skillMoves": 5,
    "playStyles": [0, 21, 22, 5, 6, 7],
    "playStylesPlus": [25],
    "eaRolesPlus": [43],
    "eaRolesPlusPlus": [139, 141],
    "clubId": 243,
    "leagueId": 53,
    "countryId": 18,
    "weakFoot": 4,
    "attributes": [97, 90, 81, 92, 37, 76],
    "metaRating": 91.05973531392576,
    "playerRoleId": 39,
    "canEvolve": false,
    "hasDynamicImage": false,
    "playerUrl": "https://assets.easysbc.io/fc26/players/231747.png",
    "newPlayer": false,
    "versionId": 1,
    "eaPlayerId": null,
    "untradeable": false,
    "owned": false,
    "name": "Kylian Mbapp\u00e9",
    "cardName": "Mbapp\u00e9",
    "price": 1015000,
    "rolesPlus": [43, 139, 141],
    "rolesPlusPlus": [43, 139, 141]
  },
  {
    "resourceId": 231443,
    "assetId": 231443,
    "preferredPosition": "ST",
    "possiblePositions": ["CAM", "RW", "ST"],
    "rating": 90,
    "metalId": 3,
    "preferredFoot": "Left",
    "skillMoves": 5,
    "playStyles": [13, 23, 25, 6, 9],
    "playStylesPlus": [21],
    "eaRolesPlus": [],
    "eaRolesPlusPlus": [136, 143],
    "clubId": 73,
    "leagueId": 16,
    "countryId": 18,
    "weakFoot": 5,
    "attributes": [91, 88, 83, 93, 50, 69],
    "metaRating": 90.43327835583206,
    "playerRoleId": 36,
    "canEvolve": false,
    "hasDynamicImage": false,
    "playerUrl": "https://assets.easysbc.io/fc26/players/231443.png",
    "newPlayer": false,
    "versionId": 1,
    "eaPlayerId": null,
    "untradeable": false,
    "owned": false,
    "name": "Ousmane Demb\u00e9l\u00e9",
    "cardName": "Demb\u00e9l\u00e9",
    "price": 263000,
    "rolesPlus": [136, 143],
    "rolesPlusPlus": [136, 143]
  },
  {
    "resourceId": 241667,
    "assetId": 241667,
    "preferredPosition": "CM",
    "possiblePositions": ["CAM", "CM"],
    "rating": 91,
    "metalId": 3,
    "preferredFoot": "Right",
    "skillMoves": 4,
    "playStyles": [11, 13, 22, 6, 8, 9],
    "playStylesPlus": [20],
    "eaRolesPlus": [22],
    "eaRolesPlusPlus": [121],
    "clubId": 116325,
    "leagueId": 2222,
    "countryId": 45,
    "weakFoot": 5,
    "attributes": [85, 87, 86, 91, 77, 75],
    "metaRating": 90.22417502924756,
    "playerRoleId": 21,
    "canEvolve": false,
    "hasDynamicImage": false,
    "playerUrl": "https://assets.easysbc.io/fc26/players/241667.png",
    "newPlayer": false,
    "versionId": 1,
    "eaPlayerId": null,
    "untradeable": false,
    "owned": false,
    "name": "Aitana Bonmat\u00ed",
    "cardName": "Aitana Bonmat\u00ed",
    "price": 91000,
    "rolesPlus": [22, 121],
    "rolesPlusPlus": [22, 121]
  },
  {
    "resourceId": 252145,
    "assetId": 252145,
    "preferredPosition": "LB",
    "possiblePositions": ["LB", "LM"],
    "rating": 86,
    "metalId": 3,
    "preferredFoot": "Left",
    "skillMoves": 3,
    "playStyles": [12, 14, 17, 21, 9],
    "playStylesPlus": [25],
    "eaRolesPlus": [],
    "eaRolesPlusPlus": [110],
    "clubId": 73,
    "leagueId": 16,
    "countryId": 38,
    "weakFoot": 4,
    "attributes": [95, 65, 76, 82, 80, 77],
    "metaRating": 90.0439625420773,
    "playerRoleId": 7,
    "canEvolve": true,
    "hasDynamicImage": false,
    "playerUrl": "https://assets.easysbc.io/fc26/players/252145.png",
    "newPlayer": false,
    "versionId": 1,
    "eaPlayerId": null,
    "untradeable": false,
    "owned": false,
    "name": "Nuno Mendes",
    "cardName": "Nuno Mendes",
    "price": 16000,
    "rolesPlus": [110],
    "rolesPlusPlus": [110]
  },
  {
    "resourceId": 230621,
    "assetId": 230621,
    "preferredPosition": "GK",
    "possiblePositions": ["GK"],
    "rating": 89,
    "metalId": 3,
    "preferredFoot": "Right",
    "skillMoves": 1,
    "playStyles": [31],
    "playStylesPlus": [35],
    "eaRolesPlus": [],
    "eaRolesPlusPlus": [101],
    "clubId": 73,
    "leagueId": 16,
    "countryId": 27,
    "weakFoot": 3,
    "attributes": [90, 83, 70, 90, 52, 87],
    "metaRating": 89.81279543686797,
    "playerRoleId": 1,
    "canEvolve": false,
    "hasDynamicImage": false,
    "playerUrl": "https://assets.easysbc.io/fc26/players/230621.png",
    "newPlayer": false,
    "versionId": 1,
    "eaPlayerId": null,
    "untradeable": false,
    "owned": false,
    "name": "Gianluigi Donnarumma",
    "cardName": "Donnarumma",
    "price": 1599000,
    "rolesPlus": [101],
    "rolesPlusPlus": [101]
  },
  {
    "resourceId": 235212,
    "assetId": 235212,
    "preferredPosition": "RB",
    "possiblePositions": ["RB", "RM"],
    "rating": 89,
    "metalId": 3,
    "preferredFoot": "Right",
    "skillMoves": 4,
    "playStyles": [12, 14, 17, 24, 25, 6],
    "playStylesPlus": [26],
    "eaRolesPlus": [46],
    "eaRolesPlusPlus": [106],
    "clubId": 73,
    "leagueId": 16,
    "countryId": 129,
    "weakFoot": 4,
    "attributes": [92, 79, 82, 83, 82, 79],
    "metaRating": 89.30786052746068,
    "playerRoleId": 3,
    "canEvolve": false,
    "hasDynamicImage": false,
    "playerUrl": "https://assets.easysbc.io/fc26/players/235212.png",
    "newPlayer": false,
    "versionId": 1,
    "eaPlayerId": null,
    "untradeable": false,
    "owned": false,
    "name": "Achraf Hakimi",
    "cardName": "Hakimi",
    "price": 24000,
    "rolesPlus": [46, 106],
    "rolesPlusPlus": [46, 106]
  },
  {
    "resourceId": 209331,
    "assetId": 209331,
    "preferredPosition": "RM",
    "possiblePositions": ["RM", "RW"],
    "rating": 91,
    "metalId": 3,
    "preferredFoot": "Left",
    "skillMoves": 4,
    "playStyles": [12, 13, 20, 22, 6, 7],
    "playStylesPlus": [0],
    "eaRolesPlus": [],
    "eaRolesPlusPlus": [126, 136],
    "clubId": 9,
    "leagueId": 13,
    "countryId": 111,
    "weakFoot": 3,
    "attributes": [89, 88, 86, 90, 45, 76],
    "metaRating": 89.25705162885419,
    "playerRoleId": 26,
    "canEvolve": false,
    "hasDynamicImage": false,
    "playerUrl": "https://assets.easysbc.io/fc26/players/209331.png",
    "newPlayer": false,
    "versionId": 1,
    "eaPlayerId": null,
    "untradeable": false,
    "owned": false,
    "name": "Mohamed Salah",
    "cardName": "Salah",
    "price": 91500,
    "rolesPlus": [126, 136],
    "rolesPlusPlus": [126, 136]
  },
  {
    "resourceId": 235073,
    "assetId": 235073,
    "preferredPosition": "GK",
    "possiblePositions": ["GK"],
    "rating": 86,
    "metalId": 3,
    "preferredFoot": "Right",
    "skillMoves": 1,
    "playStyles": [30, 35],
    "playStylesPlus": [33],
    "eaRolesPlus": [],
    "eaRolesPlusPlus": [101],
    "clubId": 22,
    "leagueId": 19,
    "countryId": 47,
    "weakFoot": 3,
    "attributes": [87, 83, 64, 87, 44, 86],
    "metaRating": 88.8356835829545,
    "playerRoleId": 1,
    "canEvolve": false,
    "hasDynamicImage": false,
    "playerUrl": "https://assets.easysbc.io/fc26/players/235073.png",
    "newPlayer": false,
    "versionId": 1,
    "eaPlayerId": null,
    "untradeable": false,
    "owned": false,
    "name": "Gregor Kobel",
    "cardName": "Kobel",
    "price": 2500,
    "rolesPlus": [101],
    "rolesPlusPlus": [101]
  },
  {
    "resourceId": 212831,
    "assetId": 212831,
    "preferredPosition": "GK",
    "possiblePositions": ["GK"],
    "rating": 89,
    "metalId": 3,
    "preferredFoot": "Right",
    "skillMoves": 1,
    "playStyles": [30, 35],
    "playStylesPlus": [33],
    "eaRolesPlus": [],
    "eaRolesPlusPlus": [145],
    "clubId": 9,
    "leagueId": 13,
    "countryId": 54,
    "weakFoot": 3,
    "attributes": [86, 85, 86, 89, 56, 90],
    "metaRating": 88.83093849078345,
    "playerRoleId": 1,
    "canEvolve": false,
    "hasDynamicImage": false,
    "playerUrl": "https://assets.easysbc.io/fc26/players/212831.png",
    "newPlayer": false,
    "versionId": 1,
    "eaPlayerId": null,
    "untradeable": false,
    "owned": false,
    "name": "Alisson",
    "cardName": "Alisson",
    "price": 23250,
    "rolesPlus": [145],
    "rolesPlusPlus": [145]
  },
  {
    "resourceId": 227203,
    "assetId": 227203,
    "preferredPosition": "CM",
    "possiblePositions": ["CAM", "CDM", "CM"],
    "rating": 91,
    "metalId": 3,
    "preferredFoot": "Left",
    "skillMoves": 5,
    "playStyles": [0, 11, 13, 20, 7, 8],
    "playStylesPlus": [22],
    "eaRolesPlus": [22],
    "eaRolesPlusPlus": [121, 133],
    "clubId": 116325,
    "leagueId": 2222,
    "countryId": 45,
    "weakFoot": 5,
    "attributes": [82, 89, 90, 91, 72, 80],
    "metaRating": 88.21619803289764,
    "playerRoleId": 21,
    "canEvolve": false,
    "hasDynamicImage": false,
    "playerUrl": "https://assets.easysbc.io/fc26/players/227203.png",
    "newPlayer": false,
    "versionId": 1,
    "eaPlayerId": null,
    "untradeable": false,
    "owned": false,
    "name": "Alexia Putellas",
    "cardName": "Alexia Putellas",
    "price": 91500,
    "rolesPlus": [22, 121, 133],
    "rolesPlusPlus": [22, 121, 133]
  },
  {
    "resourceId": 203376,
    "assetId": 203376,
    "preferredPosition": "CB",
    "possiblePositions": ["CB"],
    "rating": 90,
    "metalId": 3,
    "preferredFoot": "Right",
    "skillMoves": 2,
    "playStyles": [14, 17, 19, 28, 4, 9],
    "playStylesPlus": [16],
    "eaRolesPlus": [11],
    "eaRolesPlusPlus": [113],
    "clubId": 9,
    "leagueId": 13,
    "countryId": 34,
    "weakFoot": 3,
    "attributes": [73, 60, 72, 72, 90, 87],
    "metaRating": 88.03723035053946,
    "playerRoleId": 11,
    "canEvolve": false,
    "hasDynamicImage": false,
    "playerUrl": "https://assets.easysbc.io/fc26/players/203376.png",
    "newPlayer": false,
    "versionId": 1,
    "eaPlayerId": null,
    "untradeable": false,
    "owned": false,
    "name": "Virgil van Dijk",
    "cardName": "van Dijk",
    "price": 47250,
    "rolesPlus": [11, 113],
    "rolesPlusPlus": [11, 113]
  },
  {
    "resourceId": 233419,
    "assetId": 233419,
    "preferredPosition": "LM",
    "possiblePositions": ["LM", "LW"],
    "rating": 89,
    "metalId": 3,
    "preferredFoot": "Left",
    "skillMoves": 4,
    "playStyles": [0, 2, 23, 25, 26],
    "playStylesPlus": [21],
    "eaRolesPlus": [29],
    "eaRolesPlusPlus": [130],
    "clubId": 241,
    "leagueId": 53,
    "countryId": 54,
    "weakFoot": 4,
    "attributes": [91, 84, 85, 87, 53, 75],
    "metaRating": 87.97463134088844,
    "playerRoleId": 30,
    "canEvolve": false,
    "hasDynamicImage": false,
    "playerUrl": "https://assets.easysbc.io/fc26/players/233419.png",
    "newPlayer": false,
    "versionId": 1,
    "eaPlayerId": null,
    "untradeable": false,
    "owned": false,
    "name": "Raphinha",
    "cardName": "Raphinha",
    "price": 36000,
    "rolesPlus": [29, 130],
    "rolesPlusPlus": [29, 130]
  },
  {
    "resourceId": 238794,
    "assetId": 238794,
    "preferredPosition": "LW",
    "possiblePositions": ["LM", "LW", "ST"],
    "rating": 89,
    "metalId": 3,
    "preferredFoot": "Right",
    "skillMoves": 5,
    "playStyles": [0, 1, 13, 21, 22, 7],
    "playStylesPlus": [25],
    "eaRolesPlus": [30, 38],
    "eaRolesPlusPlus": [139, 143],
    "clubId": 243,
    "leagueId": 53,
    "countryId": 54,
    "weakFoot": 4,
    "attributes": [95, 84, 81, 91, 29, 69],
    "metaRating": 87.92818433731307,
    "playerRoleId": 39,
    "canEvolve": false,
    "hasDynamicImage": false,
    "playerUrl": "https://assets.easysbc.io/fc26/players/238794.png",
    "newPlayer": false,
    "versionId": 1,
    "eaPlayerId": null,
    "untradeable": false,
    "owned": false,
    "name": "Vini Jr.",
    "cardName": "Vini Jr.",
    "price": 99500,
    "rolesPlus": [30, 38, 139, 143],
    "rolesPlusPlus": [30, 38, 139, 143]
  },
  {
    "resourceId": 192119,
    "assetId": 192119,
    "preferredPosition": "GK",
    "possiblePositions": ["GK"],
    "rating": 89,
    "metalId": 3,
    "preferredFoot": "Left",
    "skillMoves": 1,
    "playStyles": [30, 33],
    "playStylesPlus": [32],
    "eaRolesPlus": [],
    "eaRolesPlusPlus": [101],
    "clubId": 243,
    "leagueId": 53,
    "countryId": 7,
    "weakFoot": 3,
    "attributes": [85, 89, 76, 90, 46, 88],
    "metaRating": 87.60915844459323,
    "playerRoleId": 1,
    "canEvolve": false,
    "hasDynamicImage": false,
    "playerUrl": "https://assets.easysbc.io/fc26/players/192119.png",
    "newPlayer": false,
    "versionId": 1,
    "eaPlayerId": null,
    "untradeable": false,
    "owned": false,
    "name": "Thibaut Courtois",
    "cardName": "Courtois",
    "price": 23500,
    "rolesPlus": [101],
    "rolesPlusPlus": [101]
  },
  {
    "resourceId": 256630,
    "assetId": 256630,
    "preferredPosition": "CAM",
    "possiblePositions": ["CAM", "CM", "ST"],
    "rating": 89,
    "metalId": 3,
    "preferredFoot": "Right",
    "skillMoves": 4,
    "playStyles": [0, 1, 13, 20, 22, 6],
    "playStylesPlus": [8],
    "eaRolesPlus": [32],
    "eaRolesPlusPlus": [131, 143],
    "clubId": 9,
    "leagueId": 13,
    "countryId": 21,
    "weakFoot": 4,
    "attributes": [80, 82, 88, 90, 54, 67],
    "metaRating": 87.46056397758544,
    "playerRoleId": 31,
    "canEvolve": false,
    "hasDynamicImage": false,
    "playerUrl": "https://assets.easysbc.io/fc26/players/256630.png",
    "newPlayer": false,
    "versionId": 1,
    "eaPlayerId": null,
    "untradeable": false,
    "owned": false,
    "name": "Florian Wirtz",
    "cardName": "Wirtz",
    "price": 23000,
    "rolesPlus": [32, 131, 143],
    "rolesPlusPlus": [32, 131, 143]
  },
  {
    "resourceId": 227102,
    "assetId": 227102,
    "preferredPosition": "RW",
    "possiblePositions": ["RM", "RW"],
    "rating": 90,
    "metalId": 3,
    "preferredFoot": "Right",
    "skillMoves": 5,
    "playStyles": [0, 10, 20, 22, 25],
    "playStylesPlus": [23],
    "eaRolesPlus": [],
    "eaRolesPlusPlus": [126, 136],
    "clubId": 116325,
    "leagueId": 2222,
    "countryId": 36,
    "weakFoot": 5,
    "attributes": [89, 87, 88, 90, 47, 76],
    "metaRating": 86.9982953829164,
    "playerRoleId": 26,
    "canEvolve": false,
    "hasDynamicImage": false,
    "playerUrl": "https://assets.easysbc.io/fc26/players/227102.png",
    "newPlayer": false,
    "versionId": 1,
    "eaPlayerId": null,
    "untradeable": false,
    "owned": false,
    "name": "Caroline Graham Hansen",
    "cardName": "Graham Hansen",
    "price": 50000,
    "rolesPlus": [126, 136],
    "rolesPlusPlus": [126, 136]
  },
  {
    "resourceId": 227323,
    "assetId": 227323,
    "preferredPosition": "LM",
    "possiblePositions": ["CAM", "LM", "LW"],
    "rating": 88,
    "metalId": 3,
    "preferredFoot": "Left",
    "skillMoves": 4,
    "playStyles": [0, 12, 25, 26, 3, 8],
    "playStylesPlus": [21],
    "eaRolesPlus": [27, 33],
    "eaRolesPlusPlus": [130, 138],
    "clubId": 116010,
    "leagueId": 2216,
    "countryId": 36,
    "weakFoot": 3,
    "attributes": [88, 82, 85, 87, 60, 69],
    "metaRating": 86.96592412571125,
    "playerRoleId": 30,
    "canEvolve": true,
    "hasDynamicImage": false,
    "playerUrl": "https://assets.easysbc.io/fc26/players/227323.png",
    "newPlayer": false,
    "versionId": 1,
    "eaPlayerId": null,
    "untradeable": false,
    "owned": false,
    "name": "Guro Reiten",
    "cardName": "Reiten",
    "price": 9500,
    "rolesPlus": [27, 33, 130, 138],
    "rolesPlusPlus": [27, 33, 130, 138]
  },
  {
    "resourceId": 239053,
    "assetId": 239053,
    "preferredPosition": "CM",
    "possiblePositions": ["CDM", "CM", "RB"],
    "rating": 89,
    "metalId": 3,
    "preferredFoot": "Right",
    "skillMoves": 3,
    "playStyles": [10, 16, 18, 19, 2, 21],
    "playStylesPlus": [26],
    "eaRolesPlus": [5, 20, 22],
    "eaRolesPlusPlus": [116, 118],
    "clubId": 243,
    "leagueId": 53,
    "countryId": 60,
    "weakFoot": 4,
    "attributes": [88, 84, 84, 84, 83, 85],
    "metaRating": 86.75829816403915,
    "playerRoleId": 3,
    "canEvolve": false,
    "hasDynamicImage": false,
    "playerUrl": "https://assets.easysbc.io/fc26/players/239053.png",
    "newPlayer": false,
    "versionId": 1,
    "eaPlayerId": null,
    "untradeable": false,
    "owned": false,
    "name": "Federico Valverde",
    "cardName": "Valverde",
    "price": 36500,
    "rolesPlus": [5, 20, 22, 116, 118],
    "rolesPlusPlus": [5, 20, 22, 116, 118]
  },
  {
    "resourceId": 264012,
    "assetId": 264012,
    "preferredPosition": "ST",
    "possiblePositions": ["CAM", "LW", "ST"],
    "rating": 88,
    "metalId": 3,
    "preferredFoot": "Right",
    "skillMoves": 4,
    "playStyles": [0, 20, 23, 25, 6],
    "playStylesPlus": [22],
    "eaRolesPlus": [41],
    "eaRolesPlusPlus": [139, 143],
    "clubId": 116302,
    "leagueId": 2221,
    "countryId": 95,
    "weakFoot": 5,
    "attributes": [92, 87, 79, 89, 45, 81],
    "metaRating": 86.71058302182054,
    "playerRoleId": 39,
    "canEvolve": true,
    "hasDynamicImage": false,
    "playerUrl": "https://assets.easysbc.io/fc26/players/264012.png",
    "newPlayer": false,
    "versionId": 1,
    "eaPlayerId": null,
    "untradeable": false,
    "owned": false,
    "name": "Sophia Wilson",
    "cardName": "Wilson",
    "price": 9800,
    "rolesPlus": [41, 139, 143],
    "rolesPlusPlus": [41, 139, 143]
  }
]
